langreact/core/__init__.py
langreact/core/application.py
langreact/core/builder/__init__.py
langreact/core/builder/output_builder.py
langreact/core/common/__init__.py
langreact/core/common/agent.py
langreact/core/common/chunk.py
langreact/core/common/event.py
langreact/core/common/event_manager.py
langreact/core/common/feedback_chunk.py
langreact/core/configure/__init__.py
langreact/core/configure/configure.py
langreact/core/configure/default.py
langreact/core/configure/logging.conf
langreact/core/constants.py
langreact/core/context.py
langreact/core/flow.py
langreact/core/memory/__init__.py
langreact/core/memory/memory.py
langreact/core/memory/memory_chunk.py
langreact/core/memory/memory_index.py
langreact/core/modifier/__init__.py
langreact/core/modifier/chunk_modifier.py
langreact/core/modifier/context_modifier.py
langreact/core/observer/__init__.py
langreact/core/observer/feedback.py
langreact/core/observer/observer.py
langreact/core/observer/observer_manager.py
langreact/core/params.py
langreact/core/planning/__init__.py
langreact/core/planning/agent.py
langreact/core/plugin/__init__.py
langreact/core/plugin/base.py
langreact/core/plugin/plugins.py
langreact/core/plugin/qwen_plugin.py
langreact/core/steps.py
langreact/core/tools.py
langreact-0.3.1.dist-info/LICENSE
langreact-0.3.1.dist-info/METADATA
langreact-0.3.1.dist-info/WHEEL
langreact-0.3.1.dist-info/RECORD
