Metadata-Version: 2.1
Name: langreact
Version: 0.3.1
Summary: LangReact Project
License: MIT
Author: zhangli
Author-email: max_and_min@163.com
Requires-Python: >=3.11,<4.0
Classifier: License :: OSI Approved :: MIT License
Classifier: Programming Language :: Python :: 3
Classifier: Programming Language :: Python :: 3.11
Classifier: Programming Language :: Python :: 3.12
Requires-Dist: dashscope (>=1.17.1,<2.0.0)
Requires-Dist: langchain (>=0.1.16,<0.2.0)
Requires-Dist: milvus (==2.3.5)
Requires-Dist: openai (>=1.23.2,<2.0.0)
Requires-Dist: pymilvus (>=2.4.0,<3.0.0)
Requires-Dist: requests (>=2.31.0,<3.0.0)
Requires-Dist: sentence-transformers (>=2.7.0,<3.0.0)
